{"foreground":{"doctor":{"color of coat":"pink","color of shirt":"blue","attire":"white and blue coat","glasses":"clear glasses","stethoscope":"hanging from coat","medical bag":"no bag visible","pen":"no pen visible","cell phone":"no cell phone visible","gender":"male","clothing":"white lab coat"},"nurse":{"gender":"male","clothing":"no"}},"background":{"office":{"chairs":"no chairs visible","desk":"no desk visible"},"mirror":{"mirror on wall":"no mirror visible"},"medical equipment":{"medical equipment":"no medical equipment visible"}}}